{"telemetry_id":"fzjlbmzl7vjwge7f","slug":"exercise-postcard","agent":"vscode","tutorial_started_at":1717017335698,"steps":[{"slug":"00-welcome","position":0,"files":[{"path":".learn/exercises/00-welcome/README.es.md","name":"README.es.md","hidden":true},{"path":".learn/exercises/00-welcome/README.md","name":"README.md","hidden":true}],"ai_interactions":[],"compilations":[{"starting_at":1717026902283,"source_code":"","stdout":"U3VjY2Vzc2Z1bGx5IGJ1aWx0IHlvdXIgSFRNTA==","ended_at":"2024-05-29T23:55:02.283Z","exit_code":0}],"tests":[],"is_testeable":false},{"slug":"01-design","position":1,"files":[{"path":".learn/exercises/01-design/README.es.md","name":"README.es.md","hidden":true},{"path":".learn/exercises/01-design/README.md","name":"README.md","hidden":true}],"ai_interactions":[],"compilations":[{"starting_at":1717026908497,"source_code":"","stdout":"U3VjY2Vzc2Z1bGx5IGJ1aWx0IHlvdXIgSFRNTA==","ended_at":"2024-05-29T23:55:08.497Z","exit_code":0}],"tests":[],"is_testeable":false,"opened_at":1717017529570,"completed_at":1717017566906},{"slug":"02-create-index","position":2,"files":[{"path":".learn/exercises/02-create-index/README.es.md","name":"README.es.md","hidden":true},{"path":".learn/exercises/02-create-index/README.md","name":"README.md","hidden":true},{"path":".learn/exercises/02-create-index/test.js","name":"test.js","hidden":true}],"ai_interactions":[],"compilations":[{"starting_at":1717017671032,"source_code":"","stdout":"U3VjY2Vzc2Z1bGx5IGJ1aWx0IHlvdXIgSFRNTA==","ended_at":"2024-05-29T21:21:11.032Z","exit_code":0}],"tests":[{"starting_at":1717017677176,"ended_at":1717017682023,"source_code":"","stdout":"G1szMm3inIUgQWxsIHRlc3RzIHBhc3NlZCBzdWNjZXNzZnVsbHkhG1szOW0=","stderr":"","exit_code":0},{"starting_at":1717017748910,"ended_at":1717017750198,"source_code":"","stdout":"G1szMm3inIUgQWxsIHRlc3RzIHBhc3NlZCBzdWNjZXNzZnVsbHkhG1szOW0=","stderr":"","exit_code":0},{"starting_at":1717019909484,"ended_at":1717019910819,"source_code":"","stdout":"G1szMm3inIUgQWxsIHRlc3RzIHBhc3NlZCBzdWNjZXNzZnVsbHkhG1szOW0=","stderr":"","exit_code":0},{"starting_at":1717026915742,"ended_at":1717026917037,"source_code":"","stdout":"G1szMm3inIUgQWxsIHRlc3RzIHBhc3NlZCBzdWNjZXNzZnVsbHkhG1szOW0=","stderr":"","exit_code":0}],"is_testeable":true,"opened_at":1717017566906,"completed_at":1717026917037},{"slug":"03-add-first-html","position":3,"files":[{"path":".learn/exercises/03-add-first-html/README.es.md","name":"README.es.md","hidden":true},{"path":".learn/exercises/03-add-first-html/README.md","name":"README.md","hidden":true}],"ai_interactions":[],"compilations":[{"starting_at":1717017724990,"source_code":"","stdout":"U3VjY2Vzc2Z1bGx5IGJ1aWx0IHlvdXIgSFRNTA==","ended_at":"2024-05-29T21:22:04.990Z","exit_code":0}],"tests":[],"is_testeable":false,"opened_at":1717017685597,"completed_at":1717017739568},{"slug":"04-build-the-website","position":4,"files":[{"path":".learn/exercises/04-build-the-website/README.es.md","name":"README.es.md","hidden":true},{"path":".learn/exercises/04-build-the-website/README.md","name":"README.md","hidden":true}],"ai_interactions":[],"compilations":[{"starting_at":1717017805382,"source_code":"","stdout":"U3VjY2Vzc2Z1bGx5IGJ1aWx0IHlvdXIgSFRNTA==","ended_at":"2024-05-29T21:23:25.382Z","exit_code":0}],"tests":[],"is_testeable":false,"opened_at":1717017778708,"completed_at":1717017811853},{"slug":"05-how-to-start","position":5,"files":[{"path":".learn/exercises/05-how-to-start/README.es.md","name":"README.es.md","hidden":true},{"path":".learn/exercises/05-how-to-start/README.md","name":"README.md","hidden":true}],"ai_interactions":[],"compilations":[],"tests":[],"is_testeable":false,"opened_at":1717017811853,"completed_at":1717017905766},{"slug":"06-lets-start-building","position":6,"files":[{"path":".learn/exercises/06-lets-start-building/README.es.md","name":"README.es.md","hidden":true},{"path":".learn/exercises/06-lets-start-building/README.md","name":"README.md","hidden":true},{"path":".learn/exercises/06-lets-start-building/test.js","name":"test.js","hidden":true}],"ai_interactions":[],"compilations":[{"starting_at":1717018027384,"source_code":"","stdout":"U3VjY2Vzc2Z1bGx5IGJ1aWx0IHlvdXIgSFRNTA==","ended_at":"2024-05-29T21:27:07.384Z","exit_code":0}],"tests":[{"starting_at":1717018031460,"ended_at":1717018032931,"source_code":"","stdout":"G1szMm3inIUgQWxsIHRlc3RzIHBhc3NlZCBzdWNjZXNzZnVsbHkhG1szOW0=","stderr":"","exit_code":0},{"starting_at":1717019923446,"ended_at":1717019924670,"source_code":"","stdout":"G1szMm3inIUgQWxsIHRlc3RzIHBhc3NlZCBzdWNjZXNzZnVsbHkhG1szOW0=","stderr":"","exit_code":0}],"is_testeable":true,"opened_at":1717017905766,"completed_at":1717019924670},{"slug":"07-the-first-div","position":7,"files":[{"path":".learn/exercises/07-the-first-div/README.es.md","name":"README.es.md","hidden":true},{"path":".learn/exercises/07-the-first-div/README.md","name":"README.md","hidden":true},{"path":".learn/exercises/07-the-first-div/test.js","name":"test.js","hidden":true}],"ai_interactions":[],"compilations":[{"starting_at":1717019531557,"source_code":"","stdout":"U3VjY2Vzc2Z1bGx5IGJ1aWx0IHlvdXIgSFRNTA==","ended_at":"2024-05-29T21:52:11.557Z","exit_code":0}],"tests":[{"starting_at":1717019634992,"ended_at":1717019636443,"source_code":"","stdout":"G1szMm3inIUgQWxsIHRlc3RzIHBhc3NlZCBzdWNjZXNzZnVsbHkhG1szOW0=","stderr":"","exit_code":0},{"starting_at":1717019928325,"ended_at":1717019929577,"source_code":"","stdout":"G1szMm3inIUgQWxsIHRlc3RzIHBhc3NlZCBzdWNjZXNzZnVsbHkhG1szOW0=","stderr":"","exit_code":0}],"is_testeable":true,"opened_at":1717019439612,"completed_at":1717019929577},{"slug":"08-adding-styles","position":8,"files":[{"path":".learn/exercises/08-adding-styles/README.es.md","name":"README.es.md","hidden":true},{"path":".learn/exercises/08-adding-styles/README.md","name":"README.md","hidden":true},{"path":".learn/exercises/08-adding-styles/test.js","name":"test.js","hidden":true}],"ai_interactions":[],"compilations":[{"starting_at":1717019948244,"source_code":"","stdout":"U3VjY2Vzc2Z1bGx5IGJ1aWx0IHlvdXIgSFRNTA==","ended_at":"2024-05-29T21:59:08.244Z","exit_code":0}],"tests":[{"starting_at":1717019958210,"ended_at":1717019959579,"source_code":"","stdout":"G1szMm3inIUgQWxsIHRlc3RzIHBhc3NlZCBzdWNjZXNzZnVsbHkhG1szOW0=","stderr":"","exit_code":0}],"is_testeable":true,"opened_at":1717019641613,"completed_at":1717019959579},{"slug":"08.1-red-borders","position":9,"files":[{"path":".learn/exercises/08.1-red-borders/README.es.md","name":"README.es.md","hidden":true},{"path":".learn/exercises/08.1-red-borders/README.md","name":"README.md","hidden":true},{"path":".learn/exercises/08.1-red-borders/test.js","name":"test.js","hidden":true}],"ai_interactions":[],"compilations":[{"starting_at":1717020082630,"source_code":"","stdout":"U3VjY2Vzc2Z1bGx5IGJ1aWx0IHlvdXIgSFRNTA==","ended_at":"2024-05-29T22:01:22.630Z","exit_code":0}],"tests":[{"starting_at":1717020086197,"ended_at":1717020087568,"source_code":"","stdout":"G1szMm3inIUgQWxsIHRlc3RzIHBhc3NlZCBzdWNjZXNzZnVsbHkhG1szOW0=","stderr":"","exit_code":0}],"is_testeable":true,"opened_at":1717019961694,"completed_at":1717020087568},{"slug":"09-connecting-stylesheet","position":10,"files":[{"path":".learn/exercises/09-connecting-stylesheet/README.es.md","name":"README.es.md","hidden":true},{"path":".learn/exercises/09-connecting-stylesheet/README.md","name":"README.md","hidden":true},{"path":".learn/exercises/09-connecting-stylesheet/test.js","name":"test.js","hidden":true}],"ai_interactions":[],"compilations":[{"starting_at":1717020612145,"source_code":"","stdout":"U3VjY2Vzc2Z1bGx5IGJ1aWx0IHlvdXIgSFRNTA==","ended_at":"2024-05-29T22:10:12.145Z","exit_code":0},{"starting_at":1717020658536,"source_code":"","stdout":"U3VjY2Vzc2Z1bGx5IGJ1aWx0IHlvdXIgSFRNTA==","ended_at":"2024-05-29T22:10:58.536Z","exit_code":0},{"starting_at":1717020661019,"source_code":"","stdout":"U3VjY2Vzc2Z1bGx5IGJ1aWx0IHlvdXIgSFRNTA==","ended_at":"2024-05-29T22:11:01.019Z","exit_code":0},{"starting_at":1717020665529,"source_code":"","stdout":"U3VjY2Vzc2Z1bGx5IGJ1aWx0IHlvdXIgSFRNTA==","ended_at":"2024-05-29T22:11:05.529Z","exit_code":0}],"tests":[{"starting_at":1717020700962,"ended_at":1717020702417,"source_code":"","stdout":"G1szMm3inIUgQWxsIHRlc3RzIHBhc3NlZCBzdWNjZXNzZnVsbHkhG1szOW0=","stderr":"","exit_code":0}],"is_testeable":true,"opened_at":1717020157803,"completed_at":1717020702417},{"slug":"10-center-postcard","position":11,"files":[{"path":".learn/exercises/10-center-postcard/README.es.md","name":"README.es.md","hidden":true},{"path":".learn/exercises/10-center-postcard/README.md","name":"README.md","hidden":true},{"path":".learn/exercises/10-center-postcard/test.js","name":"test.js","hidden":true}],"ai_interactions":[],"compilations":[{"starting_at":1717020971972,"source_code":"","stdout":"U3VjY2Vzc2Z1bGx5IGJ1aWx0IHlvdXIgSFRNTA==","ended_at":"2024-05-29T22:16:11.972Z","exit_code":0}],"tests":[{"starting_at":1717020977520,"ended_at":1717020979020,"source_code":"","stdout":"G1szMm3inIUgQWxsIHRlc3RzIHBhc3NlZCBzdWNjZXNzZnVsbHkhG1szOW0=","stderr":"","exit_code":0}],"is_testeable":true,"opened_at":1717020706774,"completed_at":1717020979020},{"slug":"11-postcard-divisions","position":12,"files":[{"path":".learn/exercises/11-postcard-divisions/README.es.md","name":"README.es.md","hidden":true},{"path":".learn/exercises/11-postcard-divisions/README.md","name":"README.md","hidden":true},{"path":".learn/exercises/11-postcard-divisions/test.js","name":"test.js","hidden":true}],"ai_interactions":[],"compilations":[{"starting_at":1717021338574,"source_code":"","stdout":"U3VjY2Vzc2Z1bGx5IGJ1aWx0IHlvdXIgSFRNTA==","ended_at":"2024-05-29T22:22:18.574Z","exit_code":0},{"starting_at":1717021347580,"source_code":"","stdout":"U3VjY2Vzc2Z1bGx5IGJ1aWx0IHlvdXIgSFRNTA==","ended_at":"2024-05-29T22:22:27.580Z","exit_code":0},{"starting_at":1717021349905,"source_code":"","stdout":"U3VjY2Vzc2Z1bGx5IGJ1aWx0IHlvdXIgSFRNTA==","ended_at":"2024-05-29T22:22:29.905Z","exit_code":0}],"tests":[{"starting_at":1717021388246,"ended_at":1717021389757,"source_code":"","stdout":"G1szMm3inIUgQWxsIHRlc3RzIHBhc3NlZCBzdWNjZXNzZnVsbHkhG1szOW0=","stderr":"","exit_code":0}],"is_testeable":true,"opened_at":1717020983622,"completed_at":1717021389757},{"slug":"11.1-header-content","position":13,"files":[{"path":".learn/exercises/11.1-header-content/README.es.md","name":"README.es.md","hidden":true},{"path":".learn/exercises/11.1-header-content/README.md","name":"README.md","hidden":true},{"path":".learn/exercises/11.1-header-content/solution.hide.css","name":"solution.hide.css","hidden":true},{"path":".learn/exercises/11.1-header-content/solution.hide.html","name":"solution.hide.html","hidden":true},{"path":".learn/exercises/11.1-header-content/test.js","name":"test.js","hidden":true}],"ai_interactions":[],"compilations":[{"starting_at":1717021637247,"source_code":"","stdout":"U3VjY2Vzc2Z1bGx5IGJ1aWx0IHlvdXIgSFRNTA==","ended_at":"2024-05-29T22:27:17.247Z","exit_code":0}],"tests":[{"starting_at":1717021657179,"ended_at":1717021658707,"source_code":"","stdout":"G1szMm3inIUgQWxsIHRlc3RzIHBhc3NlZCBzdWNjZXNzZnVsbHkhG1szOW0=","stderr":"","exit_code":0}],"is_testeable":true,"opened_at":1717021410536,"completed_at":1717021658707},{"slug":"11.2-header-styles","position":14,"files":[{"path":".learn/exercises/11.2-header-styles/README.es.md","name":"README.es.md","hidden":true},{"path":".learn/exercises/11.2-header-styles/README.md","name":"README.md","hidden":true},{"path":".learn/exercises/11.2-header-styles/test.js","name":"test.js","hidden":true}],"ai_interactions":[],"compilations":[{"starting_at":1717022104437,"source_code":"","stdout":"U3VjY2Vzc2Z1bGx5IGJ1aWx0IHlvdXIgSFRNTA==","ended_at":"2024-05-29T22:35:04.437Z","exit_code":0}],"tests":[{"starting_at":1717022154796,"ended_at":1717022156324,"source_code":"","stdout":"G1szMm3inIUgQWxsIHRlc3RzIHBhc3NlZCBzdWNjZXNzZnVsbHkhG1szOW0=","stderr":"","exit_code":0}],"is_testeable":true,"opened_at":1717021661383,"completed_at":1717022156324},{"slug":"12-split-postcard-body","position":15,"files":[{"path":".learn/exercises/12-split-postcard-body/README.es.md","name":"README.es.md","hidden":true},{"path":".learn/exercises/12-split-postcard-body/README.md","name":"README.md","hidden":true},{"path":".learn/exercises/12-split-postcard-body/test.js","name":"test.js","hidden":true}],"ai_interactions":[],"compilations":[{"starting_at":1717023256830,"source_code":"","stdout":"U3VjY2Vzc2Z1bGx5IGJ1aWx0IHlvdXIgSFRNTA==","ended_at":"2024-05-29T22:54:16.830Z","exit_code":0}],"tests":[{"starting_at":1717023265186,"ended_at":1717023266769,"source_code":"","stdout":"G1szMm3inIUgQWxsIHRlc3RzIHBhc3NlZCBzdWNjZXNzZnVsbHkhG1szOW0=","stderr":"","exit_code":0}],"is_testeable":true,"opened_at":1717022159688,"completed_at":1717023266770},{"slug":"12.1-body-content","position":16,"files":[{"path":".learn/exercises/12.1-body-content/README.es.md","name":"README.es.md","hidden":true},{"path":".learn/exercises/12.1-body-content/README.md","name":"README.md","hidden":true},{"path":".learn/exercises/12.1-body-content/test.js","name":"test.js","hidden":true}],"ai_interactions":[],"compilations":[{"starting_at":1717023691189,"source_code":"","stdout":"U3VjY2Vzc2Z1bGx5IGJ1aWx0IHlvdXIgSFRNTA==","ended_at":"2024-05-29T23:01:31.189Z","exit_code":0},{"starting_at":1717023753653,"source_code":"","stdout":"U3VjY2Vzc2Z1bGx5IGJ1aWx0IHlvdXIgSFRNTA==","ended_at":"2024-05-29T23:02:33.653Z","exit_code":0},{"starting_at":1717023864211,"source_code":"","stdout":"U3VjY2Vzc2Z1bGx5IGJ1aWx0IHlvdXIgSFRNTA==","ended_at":"2024-05-29T23:04:24.211Z","exit_code":0},{"starting_at":1717025355887,"source_code":"","stdout":"U3VjY2Vzc2Z1bGx5IGJ1aWx0IHlvdXIgSFRNTA==","ended_at":"2024-05-29T23:29:15.887Z","exit_code":0},{"starting_at":1717025792825,"source_code":"","stdout":"U3VjY2Vzc2Z1bGx5IGJ1aWx0IHlvdXIgSFRNTA==","ended_at":"2024-05-29T23:36:32.825Z","exit_code":0},{"starting_at":1717025798184,"source_code":"","stdout":"U3VjY2Vzc2Z1bGx5IGJ1aWx0IHlvdXIgSFRNTA==","ended_at":"2024-05-29T23:36:38.184Z","exit_code":0}],"tests":[{"starting_at":1717025812281,"ended_at":1717025813820,"source_code":"","stdout":"G1szMm3inIUgQWxsIHRlc3RzIHBhc3NlZCBzdWNjZXNzZnVsbHkhG1szOW0=","stderr":"","exit_code":0}],"is_testeable":true,"opened_at":1717023274103,"completed_at":1717025813820},{"slug":"13-check-your-code","position":17,"files":[{"path":".learn/exercises/13-check-your-code/README.es.md","name":"README.es.md","hidden":true},{"path":".learn/exercises/13-check-your-code/README.md","name":"README.md","hidden":true}],"ai_interactions":[],"compilations":[{"starting_at":1717025986887,"source_code":"","stdout":"U3VjY2Vzc2Z1bGx5IGJ1aWx0IHlvdXIgSFRNTA==","ended_at":"2024-05-29T23:39:46.887Z","exit_code":0}],"tests":[],"is_testeable":false,"opened_at":1717025816497,"completed_at":1717026022607},{"slug":"14-goodbye","position":18,"files":[{"path":".learn/exercises/14-goodbye/README.es.md","name":"README.es.md","hidden":true},{"path":".learn/exercises/14-goodbye/README.md","name":"README.md","hidden":true}],"ai_interactions":[],"compilations":[{"starting_at":1717026113173,"source_code":"","stdout":"U3VjY2Vzc2Z1bGx5IGJ1aWx0IHlvdXIgSFRNTA==","ended_at":"2024-05-29T23:41:53.173Z","exit_code":0},{"starting_at":1717026133157,"source_code":"","stdout":"U3VjY2Vzc2Z1bGx5IGJ1aWx0IHlvdXIgSFRNTA==","ended_at":"2024-05-29T23:42:13.157Z","exit_code":0},{"starting_at":1717026152348,"source_code":"","stdout":"U3VjY2Vzc2Z1bGx5IGJ1aWx0IHlvdXIgSFRNTA==","ended_at":"2024-05-29T23:42:32.348Z","exit_code":0},{"starting_at":1717026154049,"source_code":"","stdout":"U3VjY2Vzc2Z1bGx5IGJ1aWx0IHlvdXIgSFRNTA==","ended_at":"2024-05-29T23:42:34.049Z","exit_code":0},{"starting_at":1717026155571,"source_code":"","stdout":"U3VjY2Vzc2Z1bGx5IGJ1aWx0IHlvdXIgSFRNTA==","ended_at":"2024-05-29T23:42:35.571Z","exit_code":0},{"starting_at":1717026173618,"source_code":"","stdout":"U3VjY2Vzc2Z1bGx5IGJ1aWx0IHlvdXIgSFRNTA==","ended_at":"2024-05-29T23:42:53.618Z","exit_code":0},{"starting_at":1717026201677,"source_code":"","stdout":"U3VjY2Vzc2Z1bGx5IGJ1aWx0IHlvdXIgSFRNTA==","ended_at":"2024-05-29T23:43:21.677Z","exit_code":0},{"starting_at":1717026226384,"source_code":"","stdout":"U3VjY2Vzc2Z1bGx5IGJ1aWx0IHlvdXIgSFRNTA==","ended_at":"2024-05-29T23:43:46.384Z","exit_code":0},{"starting_at":1717026258843,"source_code":"","stdout":"U3VjY2Vzc2Z1bGx5IGJ1aWx0IHlvdXIgSFRNTA==","ended_at":"2024-05-29T23:44:18.843Z","exit_code":0},{"starting_at":1717026271310,"source_code":"","stdout":"U3VjY2Vzc2Z1bGx5IGJ1aWx0IHlvdXIgSFRNTA==","ended_at":"2024-05-29T23:44:31.310Z","exit_code":0},{"starting_at":1717026373923,"source_code":"","stdout":"U3VjY2Vzc2Z1bGx5IGJ1aWx0IHlvdXIgSFRNTA==","ended_at":"2024-05-29T23:46:13.923Z","exit_code":0},{"starting_at":1717026501326,"source_code":"","stdout":"U3VjY2Vzc2Z1bGx5IGJ1aWx0IHlvdXIgSFRNTA==","ended_at":"2024-05-29T23:48:21.326Z","exit_code":0},{"starting_at":1717026589806,"source_code":"","stdout":"U3VjY2Vzc2Z1bGx5IGJ1aWx0IHlvdXIgSFRNTA==","ended_at":"2024-05-29T23:49:49.806Z","exit_code":0},{"starting_at":1717026673742,"source_code":"","stdout":"U3VjY2Vzc2Z1bGx5IGJ1aWx0IHlvdXIgSFRNTA==","ended_at":"2024-05-29T23:51:13.742Z","exit_code":0},{"starting_at":1717026696776,"source_code":"","stdout":"U3VjY2Vzc2Z1bGx5IGJ1aWx0IHlvdXIgSFRNTA==","ended_at":"2024-05-29T23:51:36.776Z","exit_code":0},{"starting_at":1717026698883,"source_code":"","stdout":"U3VjY2Vzc2Z1bGx5IGJ1aWx0IHlvdXIgSFRNTA==","ended_at":"2024-05-29T23:51:38.883Z","exit_code":0}],"tests":[],"is_testeable":false,"opened_at":1717026022607,"completed_at":1717026907871}],"workout_session":[{"started_at":1717017335698}],"last_interaction_at":1717026921429}